[
  {"id": "C001", "title": "Budget Bevroren", "description": "De CFO bevriest per direct alle IT-budgetten wegens tegenvallende kwartaalcijfers.", "effect": {"xp": 0, "budget": -300, "security": 0, "stakeholderImpact": -10, "hp": -10, "chaos": 10}, "severity": 3},
  {"id": "C002", "title": "Ransomware-aanval", "description": "Een ransomware-groep versleutelt kritieke fileshares. Losgeld gevraagd in Bitcoin.", "effect": {"xp": 5, "budget": -500, "security": -40, "stakeholderImpact": -25, "hp": -50, "chaos": 25}, "severity": 5},
  {"id": "C003", "title": "NIS2-deadline Nadert", "description": "De NIS2-richtlijn wordt actief geimplementeerd. Compliance-gap ontdekt.", "effect": {"xp": 10, "budget": -400, "security": -20, "stakeholderImpact": -15, "hp": -20, "chaos": 15}, "severity": 4},
  {"id": "C004", "title": "DORA-audit", "description": "De DORA-toezichthouder eist bewijs van operationele veerkracht binnen 30 dagen.", "effect": {"xp": 10, "budget": -350, "security": -15, "stakeholderImpact": -10, "hp": -15, "chaos": 15}, "severity": 4},
  {"id": "C005", "title": "AI Act Compliance-schok", "description": "Je high-risk AI-systeem valt onder de EU AI Act. Documentatie ontbreekt.", "effect": {"xp": 15, "budget": -300, "security": -10, "stakeholderImpact": -15, "hp": -20, "chaos": 15}, "severity": 4},
  {"id": "C006", "title": "CEO Wisselt Strategie", "description": "De CEO kondigt een pivot aan. Alle lopende roadmaps zijn achterhaald.", "effect": {"xp": 5, "budget": -200, "security": 0, "stakeholderImpact": -20, "hp": -25, "chaos": 20}, "severity": 4},
  {"id": "C007", "title": "Key-Architect Vertrekt", "description": "Je senior architect neemt ontslag en gaat naar de concurrent.", "effect": {"xp": 0, "budget": -150, "security": -10, "stakeholderImpact": -15, "hp": -30, "chaos": 15}, "severity": 4},
  {"id": "C008", "title": "Legacy-server Crasht", "description": "De mainframe uit 1998 stort in. Niemand herinnert zich het root-wachtwoord.", "effect": {"xp": 5, "budget": -250, "security": -15, "stakeholderImpact": -20, "hp": -25, "chaos": 15}, "severity": 4},
  {"id": "C009", "title": "Cloud-provider Storing", "description": "AWS eu-west-1 ligt eruit. Multi-region setup ontbreekt.", "effect": {"xp": 5, "budget": -100, "security": 0, "stakeholderImpact": -20, "hp": -20, "chaos": 15}, "severity": 3},
  {"id": "C010", "title": "Shadow IT Ontdekt", "description": "Marketing draait al een jaar een niet-goedgekeurde SaaS met klantdata.", "effect": {"xp": 10, "budget": -150, "security": -25, "stakeholderImpact": -10, "hp": -15, "chaos": 15}, "severity": 3},
  {"id": "C011", "title": "Data-lek Gepubliceerd", "description": "50.000 klantrecords verschijnen op een dark-web forum.", "effect": {"xp": 10, "budget": -450, "security": -35, "stakeholderImpact": -25, "hp": -40, "chaos": 25}, "severity": 5},
  {"id": "C012", "title": "Audit Failure", "description": "ISO 27001 audit faalt op 12 controls. Recertificering in gevaar.", "effect": {"xp": 5, "budget": -300, "security": -20, "stakeholderImpact": -20, "hp": -25, "chaos": 15}, "severity": 4},
  {"id": "C013", "title": "Vendor Gaat Failliet", "description": "Je kritieke SaaS-leverancier vraagt surseance van betaling aan.", "effect": {"xp": 5, "budget": -400, "security": -10, "stakeholderImpact": -15, "hp": -30, "chaos": 20}, "severity": 4},
  {"id": "C014", "title": "Security-incident P1", "description": "SOC meldt actieve intrusion. Incident response teams staan paraat.", "effect": {"xp": 15, "budget": -250, "security": -30, "stakeholderImpact": -15, "hp": -35, "chaos": 20}, "severity": 5},
  {"id": "C015", "title": "Kubernetes-cluster Corrupt", "description": "etcd-corruptie legt productie-cluster plat. Backup te oud.", "effect": {"xp": 10, "budget": -200, "security": -10, "stakeholderImpact": -20, "hp": -30, "chaos": 15}, "severity": 4},
  {"id": "C016", "title": "DDoS-aanval", "description": "1.2 Tbps volumetrische aanval bereikt je edge-routers. Cloudflare bibbert.", "effect": {"xp": 5, "budget": -150, "security": -15, "stakeholderImpact": -15, "hp": -25, "chaos": 15}, "severity": 4},
  {"id": "C017", "title": "Insider Threat", "description": "Een systeembeheerder blijkt data naar de concurrent te sluizen.", "effect": {"xp": 10, "budget": -200, "security": -30, "stakeholderImpact": -20, "hp": -30, "chaos": 20}, "severity": 5},
  {"id": "C018", "title": "Dependency CVE 9.8", "description": "Kritieke RCE in een populaire NPM-package. 400 microservices geraakt.", "effect": {"xp": 15, "budget": -150, "security": -25, "stakeholderImpact": -10, "hp": -20, "chaos": 15}, "severity": 4},
  {"id": "C019", "title": "Licentie-explosie", "description": "Oracle audit rekent 3x overshoot van CPU-licenties.", "effect": {"xp": 0, "budget": -500, "security": 0, "stakeholderImpact": -10, "hp": -20, "chaos": 10}, "severity": 4},
  {"id": "C020", "title": "SLA Breach", "description": "Downtime overschrijdt SLA. Klanten eisen penalty-uitkeringen.", "effect": {"xp": 5, "budget": -300, "security": 0, "stakeholderImpact": -25, "hp": -25, "chaos": 15}, "severity": 4},
  {"id": "C021", "title": "GDPR Boete", "description": "Autoriteit Persoonsgegevens legt boete van 4% jaaromzet op.", "effect": {"xp": 5, "budget": -500, "security": -10, "stakeholderImpact": -20, "hp": -30, "chaos": 20}, "severity": 5},
  {"id": "C022", "title": "Certificaat Verlopen", "description": "Wildcard-TLS expired om 03:00. Iedere API roept om oma.", "effect": {"xp": 5, "budget": -50, "security": -10, "stakeholderImpact": -15, "hp": -15, "chaos": 10}, "severity": 2},
  {"id": "C023", "title": "Domain Hijack", "description": "Registrar-account gecompromitteerd. Domein wijst naar phishing-site.", "effect": {"xp": 10, "budget": -200, "security": -30, "stakeholderImpact": -20, "hp": -25, "chaos": 20}, "severity": 5},
  {"id": "C024", "title": "Backup Corrupt", "description": "Restore-test faalt. Laatste 3 maanden backups zijn onbruikbaar.", "effect": {"xp": 10, "budget": -250, "security": -20, "stakeholderImpact": -15, "hp": -30, "chaos": 20}, "severity": 4},
  {"id": "C025", "title": "Phishing Sweep", "description": "40% van je medewerkers klikt op de simulatie. Waarschijnlijk hoger in echt.", "effect": {"xp": 10, "budget": -100, "security": -20, "stakeholderImpact": -10, "hp": -15, "chaos": 10}, "severity": 3},
  {"id": "C026", "title": "Log4Shell 2.0", "description": "Nieuwe zero-day in ubiquitous logging-lib. Patch-treadmill start weer.", "effect": {"xp": 15, "budget": -200, "security": -30, "stakeholderImpact": -10, "hp": -25, "chaos": 20}, "severity": 5},
  {"id": "C027", "title": "Interne Reorg", "description": "IT-afdeling wordt gesplitst. Team-topologieen door de shredder.", "effect": {"xp": 5, "budget": -150, "security": -5, "stakeholderImpact": -25, "hp": -25, "chaos": 20}, "severity": 4},
  {"id": "C028", "title": "M&A Aangekondigd", "description": "Bedrijf wordt overgenomen. Applicatielandschap moet integreren.", "effect": {"xp": 15, "budget": -300, "security": -10, "stakeholderImpact": -20, "hp": -30, "chaos": 20}, "severity": 5},
  {"id": "C029", "title": "Legacy COBOL Batch Faalt", "description": "Nachtelijke batch stopt op record 27.394. Niemand kent de code.", "effect": {"xp": 5, "budget": -150, "security": -5, "stakeholderImpact": -15, "hp": -20, "chaos": 15}, "severity": 3},
  {"id": "C030", "title": "Vendor Lock-in Ontdekt", "description": "Exit-clausule blijkt onbestaand. Migratie kost fortuin.", "effect": {"xp": 5, "budget": -400, "security": 0, "stakeholderImpact": -15, "hp": -20, "chaos": 15}, "severity": 4},
  {"id": "C031", "title": "Compliance-officer Vertrekt", "description": "De CISO neemt ontslag midden in audit-seizoen.", "effect": {"xp": 0, "budget": -100, "security": -20, "stakeholderImpact": -15, "hp": -25, "chaos": 15}, "severity": 4},
  {"id": "C032", "title": "Datacenter Waterschade", "description": "Airco-lek in DC-2 zet 40 racks onder water.", "effect": {"xp": 5, "budget": -450, "security": -10, "stakeholderImpact": -20, "hp": -35, "chaos": 20}, "severity": 5},
  {"id": "C033", "title": "Supply Chain Attack", "description": "Kwaadaardige update via CI/CD-pipeline vendor.", "effect": {"xp": 15, "budget": -350, "security": -35, "stakeholderImpact": -15, "hp": -35, "chaos": 25}, "severity": 5},
  {"id": "C034", "title": "SaaS Prijsverhoging 40%", "description": "Marktleider verdrievoudigt licentiekosten na acquisitie.", "effect": {"xp": 0, "budget": -400, "security": 0, "stakeholderImpact": -10, "hp": -15, "chaos": 10}, "severity": 3},
  {"id": "C035", "title": "Pentest Vernietigend", "description": "Red team wandelt binnen 2 uur naar Domain Admin.", "effect": {"xp": 15, "budget": -250, "security": -30, "stakeholderImpact": -15, "hp": -25, "chaos": 15}, "severity": 4},
  {"id": "C036", "title": "Klantopstand", "description": "Grootste klant dreigt met opzegging vanwege performance-issues.", "effect": {"xp": 5, "budget": -300, "security": 0, "stakeholderImpact": -25, "hp": -30, "chaos": 20}, "severity": 4},
  {"id": "C037", "title": "Legacy API Deprecated", "description": "Externe partner trekt v1 API in. 200 integraties breken.", "effect": {"xp": 10, "budget": -200, "security": -10, "stakeholderImpact": -15, "hp": -20, "chaos": 15}, "severity": 3},
  {"id": "C038", "title": "Kabel Doorgegraven", "description": "Bouwvakker raakt fiberpaar. Datacenter geisoleerd 8 uur.", "effect": {"xp": 5, "budget": -150, "security": -5, "stakeholderImpact": -20, "hp": -20, "chaos": 15}, "severity": 3},
  {"id": "C039", "title": "Onthullende Bloomberg-artikel", "description": "Journalist publiceert lek over interne security-praktijken.", "effect": {"xp": 5, "budget": -200, "security": -15, "stakeholderImpact": -25, "hp": -30, "chaos": 20}, "severity": 5},
  {"id": "C040", "title": "Storage Array Failure", "description": "SAN-controller crasht met dubbele disk-failure. Rebuild loopt vast.", "effect": {"xp": 10, "budget": -300, "security": -10, "stakeholderImpact": -20, "hp": -30, "chaos": 20}, "severity": 4},
  {"id": "C041", "title": "OT/IT Convergence-incident", "description": "Malware springt van kantoornetwerk naar productielijn.", "effect": {"xp": 15, "budget": -400, "security": -30, "stakeholderImpact": -20, "hp": -35, "chaos": 25}, "severity": 5},
  {"id": "C042", "title": "Quantum-hype Board-vraag", "description": "Board eist quantum-safe roadmap binnen 60 dagen.", "effect": {"xp": 20, "budget": -200, "security": -5, "stakeholderImpact": -10, "hp": -15, "chaos": 10}, "severity": 3},
  {"id": "C043", "title": "Public Cloud Kostenpiek", "description": "Ongebreidelde spend: maandbudget verdriedubbelt door runaway job.", "effect": {"xp": 5, "budget": -450, "security": 0, "stakeholderImpact": -15, "hp": -25, "chaos": 15}, "severity": 4},
  {"id": "C044", "title": "AD Domain Compromis", "description": "Golden ticket detected. Volledige AD-rebuild noodzakelijk.", "effect": {"xp": 15, "budget": -400, "security": -35, "stakeholderImpact": -20, "hp": -40, "chaos": 25}, "severity": 5},
  {"id": "C045", "title": "OSS-license Violation", "description": "AGPL-code in commercieel product. Copyleft-clan komt langs.", "effect": {"xp": 10, "budget": -350, "security": 0, "stakeholderImpact": -15, "hp": -25, "chaos": 15}, "severity": 4},
  {"id": "C046", "title": "Stroomstoring", "description": "Regionale black-out. UPS houdt 12 minuten. Generator start niet.", "effect": {"xp": 5, "budget": -200, "security": -5, "stakeholderImpact": -20, "hp": -30, "chaos": 20}, "severity": 4},
  {"id": "C047", "title": "Documentatie Ontbreekt", "description": "Nieuwe medewerker vindt geen enkele architectuurbeschrijving.", "effect": {"xp": 5, "budget": -100, "security": -10, "stakeholderImpact": -10, "hp": -15, "chaos": 10}, "severity": 2},
  {"id": "C048", "title": "Legacy-integratie Breekt", "description": "ESB-adapter uit 2007 stopt met werken na TLS 1.0-uitfasering.", "effect": {"xp": 5, "budget": -200, "security": -10, "stakeholderImpact": -15, "hp": -20, "chaos": 15}, "severity": 3},
  {"id": "C049", "title": "Twee Architecten Ruzien", "description": "Micro vs Modulith debat blokkeert alle beslissingen.", "effect": {"xp": 5, "budget": -100, "security": -5, "stakeholderImpact": -15, "hp": -20, "chaos": 15}, "severity": 3},
  {"id": "C050", "title": "IoT-fleet Gehackt", "description": "300.000 smart-devices ingezet in botnet. Aansprakelijkheid dreigt.", "effect": {"xp": 15, "budget": -400, "security": -35, "stakeholderImpact": -25, "hp": -40, "chaos": 25}, "severity": 5}
]
